CoreRPAHive/__init__.py
CoreRPAHive/version.py
CoreRPAHive/Config/CaptureScreenShotOption.py
CoreRPAHive/Config/__init__.py
CoreRPAHive/ExcelParser/ABCParserStrategy.py
CoreRPAHive/ExcelParser/DefaultParserStrategy.py
CoreRPAHive/ExcelParser/ExcelTestDataService.py
CoreRPAHive/ExcelParser/ParserContext.py
CoreRPAHive/ExcelParser/__init__.py
CoreRPAHive/ExcelTestDataRow/ExcelTestDataRow.py
CoreRPAHive/ExcelTestDataRow/MandatoryTestDataColumn.py
CoreRPAHive/ExcelTestDataRow/TestStatus.py
CoreRPAHive/ExcelTestDataRow/__init__.py
CoreRPAHive/Keywords/CoreExcelKeywords.py
CoreRPAHive/Keywords/__init__.py
CoreRPAHive/Util/CustomSelenium.py
CoreRPAHive/Util/OpenpyxlHelper.py
CoreRPAHive/Util/__init__.py
CoreRPAHive/base/__init__.py
CoreRPAHive/base/robotlibcore.py
robotframework_corerpahive-1.2.0.dist-info/METADATA
robotframework_corerpahive-1.2.0.dist-info/WHEEL
robotframework_corerpahive-1.2.0.dist-info/top_level.txt
robotframework_corerpahive-1.2.0.dist-info/RECORD
