Metadata-Version: 2.1
Name: robotframework-corerpahive
Version: 1.2.0
Summary: CoreRPAHive is a Robotic Process Automation library that allow the developer create RPA script easier and reduce complexity under robot script layer.
Home-page: https://github.com/qahive/robotframework-CoreRPAHive
Author: Atthaboon Sanurt
Author-email: UNKNOWN
License: Apache License 2.0
Keywords: robotframework testing automation rpa qahive
Platform: any
Classifier: Programming Language :: Python :: 3.6
Requires-Dist: inject (==3.3.2)
Requires-Dist: openpyxl (==2.6.2)
Requires-Dist: setuptools (==41.0.1)
Requires-Dist: Pillow (==6.2.1)
Requires-Dist: robotframework-seleniumlibrary
